hyperspace/__init__.py
hyperspace/affordances.py
hyperspace/html.py
hyperspace/hydra.py
hyperspace/rdf.py
hyperspace/turtle.py
hyperspace-0.2.0.dist-info/METADATA
hyperspace-0.2.0.dist-info/WHEEL
hyperspace-0.2.0.dist-info/top_level.txt
hyperspace-0.2.0.dist-info/RECORD
