Metadata-Version: 2.1
Name: hyperspace
Version: 0.2.0
Summary: General-purpose REST/hypermedia client.
Home-page: http://rossfenning.co.uk/
Author: Ross Fenning
Author-email: ross.fenning@gmail.com
License: GPLv3+
Platform: UNKNOWN
Classifier: License :: OSI Approved :: GNU General Public License v3 or later (GPLv3+)
Classifier: Operating System :: OS Independent
Classifier: Programming Language :: Python
Classifier: Topic :: Software Development :: Libraries :: Python Modules
Requires-Dist: requests
Requires-Dist: rdflib
Requires-Dist: rdflib-jsonld
Requires-Dist: beautifulsoup4
Requires-Dist: html5lib
Requires-Dist: uritemplate
Requires-Dist: laconia
